speechtokenizer/__init__.py
speechtokenizer/discriminators.py
speechtokenizer/model.py
speechtokenizer/modules/__init__.py
speechtokenizer/modules/conv.py
speechtokenizer/modules/lstm.py
speechtokenizer/modules/norm.py
speechtokenizer/modules/seanet.py
speechtokenizer/quantization/__init__.py
speechtokenizer/quantization/ac.py
speechtokenizer/quantization/core_vq.py
speechtokenizer/quantization/distrib.py
speechtokenizer/quantization/vq.py
speechtokenizer/trainer/__init__.py
speechtokenizer/trainer/dataset.py
speechtokenizer/trainer/loss.py
speechtokenizer/trainer/optimizer.py
speechtokenizer/trainer/tracking.py
speechtokenizer/trainer/trainer.py
speechtokenizer-1.0.1.dist-info/LICENSE
speechtokenizer-1.0.1.dist-info/METADATA
speechtokenizer-1.0.1.dist-info/WHEEL
speechtokenizer-1.0.1.dist-info/top_level.txt
speechtokenizer-1.0.1.dist-info/RECORD
