Metadata-Version: 2.1
Name: speechtokenizer
Version: 1.0.1
Summary: Unified speech tokenizer for speech language model
Home-page: https://github.com/ZhangXInFD/SpeechTokenizer
Author: Xin Zhang, Dong Zhang, Shimin Li, Yaqian Zhou, Xipeng Qiu
Author-email: xin_zhang22@m.fudan.edu.cn
License: Apache License 2.0
Classifier: Topic :: Multimedia :: Sound/Audio
Classifier: Topic :: Scientific/Engineering :: Artificial Intelligence
Classifier: License :: OSI Approved :: Apache Software License
Requires-Python: >=3.8.0
License-File: LICENSE
Requires-Dist: numpy
Requires-Dist: torch
Requires-Dist: torchaudio
Requires-Dist: einops
Requires-Dist: scipy
Requires-Dist: huggingface-hub
Requires-Dist: soundfile
Requires-Dist: matplotlib
Requires-Dist: lion-pytorch
Requires-Dist: accelerate
